dirpath/__init__.py
dirpath/dirpath.py
dirpath-1.0.1.dist-info/LICENSE
dirpath-1.0.1.dist-info/METADATA
dirpath-1.0.1.dist-info/WHEEL
dirpath-1.0.1.dist-info/top_level.txt
dirpath-1.0.1.dist-info/RECORD
