Metadata-Version: 2.1
Name: dirpath
Version: 1.0.1
Summary: A library for managing directory paths in the python environment.
Author: BreezeSun
License: MIT
License-File: LICENSE
